[
  {
    "name": "Adriana Malao and Daniel Hunter",
    "studio": "GoHoneyGo",
    "series": null,
    "description": null,
    "img": "Adriana Malao - Adriana Malao and Daniel Hunter [GoHoneyGo] (2014_HD_367_79 MB).jpg",
    "url": "$mainstorage$\\Adriana Malao - Adriana Malao and Daniel Hunter [GoHoneyGo] (2014_HD_367_79 MB).mp4",
    "tags": [],
    "rank": 0,
    "addeddt": "2017-11-01T20:35:19.47034+01:00",
    "size": 385652613,
    "Place": null,
    "Stars": [
      "Adriana Malao"
    ]
  }
]