[
  {
    "name": "Girls In Uniform",
    "studio": "21Sextury",
    "series": null,
    "description": null,
    "img": "Aletta Ocean, Shalina Divine, Lana S, Ivana Sugar, Bettina Dicapri, Amirah Adara - Girls In Uniform [21Sextury].jpg",
    "url": "$mainstorage$\\Aletta Ocean, Shalina Divine, Lana S, Ivana Sugar, Bettina Dicapri, Amirah Adara - Girls In Uniform [21Sextury].wmv",
    "tags": [
      "Group"
    ],
    "rank": 0,
    "addeddt": "2017-11-01T20:35:19.9859427+01:00",
    "size": 712756938,
    "Place": null,
    "Stars": [
      "Aletta Ocean",
      "Shalina Divine",
      "Lana S",
      "Ivana Sugar",
      "Bettina Dicapri",
      "Amirah Adara"
    ]
  },
  {
    "name": "(Un)professional -",
    "studio": "21Sextury",
    "series": "DPFanatics",
    "description": null,
    "img": "Amirah Adara - (Un)professional - [DPFanatics_21Sextury] (November 08, 2015).jpg",
    "url": "$mainstorage$\\Amirah Adara - (Un)professional - [DPFanatics_21Sextury] (November 08, 2015).mp4",
    "tags": [
      "Group",
      "DP",
      "Anal"
    ],
    "rank": 0,
    "addeddt": "2017-11-01T20:35:21.3194601+01:00",
    "size": 260325117,
    "Place": null,
    "Stars": [
      "Amirah Adara"
    ]
  },
  {
    "name": "Stocking Sex",
    "studio": "21Sextury",
    "series": "21Naturals",
    "description": null,
    "img": "Amirah Adara - Stocking Sex [21Naturals_21Sextury] (2017_HD_471_36 MB).jpg",
    "url": "$mainstorage$\\Amirah Adara - Stocking Sex [21Naturals_21Sextury] (2017_HD_471_36 MB).mp4",
    "tags": [
      "Stocking"
    ],
    "rank": 0,
    "addeddt": "2017-11-01T20:35:21.3339606+01:00",
    "size": 494258054,
    "Place": null,
    "Stars": [
      "Amirah Adara"
    ]
  },
  {
    "name": "Amirah Adara and Blanche Bradburry fucked ass to ass SZ431",
    "studio": "LegalPorno",
    "series": null,
    "description": null,
    "img": "Amirah Adara, Blanche Bradburry - Amirah Adara and Blanche Bradburry fucked ass to ass SZ431 [LegalPorno] (2015_SD_967_62 MB).jpg",
    "url": "$mainstorage$\\Amirah Adara, Blanche Bradburry - Amirah Adara and Blanche Bradburry fucked ass to ass SZ431 [LegalPorno] (2015_SD_967_62 MB).mp4",
    "tags": [
      "Anal"
    ],
    "rank": 0,
    "addeddt": "2017-11-01T20:35:21.3459596+01:00",
    "size": 1014622059,
    "Place": null,
    "Stars": [
      "Amirah Adara",
      "Blanche Bradburry"
    ]
  },
  {
    "name": "The Gapes of Amirah",
    "studio": "21Sextury",
    "series": "AssholeFever",
    "description": null,
    "img": "Amirah Adara, Kristof Cale - The Gapes of Amirah [AssholeFever_21Sextury] (2017_HD_699_29 MB).jpg",
    "url": "$mainstorage$\\Amirah Adara, Kristof Cale - The Gapes of Amirah [AssholeFever_21Sextury] (2017_HD_699_29 MB).mp4",
    "tags": [
      "Anal"
    ],
    "rank": 0,
    "addeddt": "2017-11-01T20:35:21.386459+01:00",
    "size": 733259689,
    "Place": null,
    "Stars": [
      "Amirah Adara",
      "Kristof Cale"
    ]
  },
  {
    "name": "Le Dortoir des Filles",
    "studio": "DorcelVision",
    "series": null,
    "description": null,
    "img": "Amirah Adara, Sophie Lynx - Le Dortoir des Filles [DorcelVision] (2013_HD_883_29 MB).jpg",
    "url": "$mainstorage$\\Amirah Adara, Sophie Lynx - Le Dortoir des Filles [DorcelVision] (2013_HD_883_29 MB).mp4",
    "tags": [],
    "rank": 0,
    "addeddt": "2017-11-01T20:35:21.4064593+01:00",
    "size": 272119999,
    "Place": null,
    "Stars": [
      "Amirah Adara",
      "Sophie Lynx"
    ]
  },
  {
    "name": "Europorn Birthday Bang 2 - Hardcore Cam",
    "studio": "Tainster",
    "series": "DrunkSexOrgy",
    "description": null,
    "img": "Angel Piaff, Nathaly Cherie, Amirah Adara, Anita B, Cayla Lyons - Europorn Birthday Bang 2 - Hardcore Cam [DrunkSexOrgy_Tainster] (2014_FullHD_1_48 GB).jpg",
    "url": "$mainstorage$\\Angel Piaff, Nathaly Cherie, Amirah Adara, Anita B, Cayla Lyons - Europorn Birthday Bang 2 - Hardcore Cam [DrunkSexOrgy_Tainster] (2014_FullHD_1_48 GB).mp4",
    "tags": [
      "Group",
      "Orgy"
    ],
    "rank": 0,
    "addeddt": "2017-11-01T20:35:21.8469589+01:00",
    "size": 1587186990,
    "Place": null,
    "Stars": [
      "Angel Piaff",
      "Nathaly Cherie",
      "Amirah Adara",
      "Anita B",
      "Cayla Lyons"
    ]
  },
  {
    "name": "Casual Cuties Get A High Class Lesbo Lesson In Cunt Pleasing",
    "studio": "SinDrive",
    "series": null,
    "description": null,
    "img": "Ivana Sugar, Amirah Adara, Cayla Lyons - Casual Cuties Get A High Class Lesbo Lesson In Cunt Pleasing [SinDrive] (2014_SD_662_79 MB).jpg",
    "url": "$mainstorage$\\Ivana Sugar, Amirah Adara, Cayla Lyons - Casual Cuties Get A High Class Lesbo Lesson In Cunt Pleasing [SinDrive] (2014_SD_662_79 MB).mp4",
    "tags": [
      "Anal",
      "Lesbian",
      "Group"
    ],
    "rank": 0,
    "addeddt": "2017-11-01T20:35:35.3366522+01:00",
    "size": 694986804,
    "Place": null,
    "Stars": [
      "Ivana Sugar",
      "Amirah Adara",
      "Cayla Lyons"
    ]
  },
  {
    "name": "Rocco and Kelly_ Sex Analysts, Scene 1",
    "studio": "RoccoSiffredi",
    "series": null,
    "description": null,
    "img": "Kelly Stafford, Amirah Adara, Rocco Siffredi - Rocco and Kelly_ Sex Analysts, Scene 1 [RoccoSiffredi] (2017_SD_710_68 MB).jpg",
    "url": "$mainstorage$\\Kelly Stafford, Amirah Adara, Rocco Siffredi - Rocco and Kelly_ Sex Analysts, Scene 1 [RoccoSiffredi] (2017_SD_710_68 MB).mp4",
    "tags": [
      "Anal",
      "Group"
    ],
    "rank": 0,
    "addeddt": "2017-11-01T20:35:38.4348095+01:00",
    "size": 745199396,
    "Place": null,
    "Stars": [
      "Kelly Stafford",
      "Amirah Adara",
      "Rocco Siffredi"
    ]
  },
  {
    "name": "After Hours Fun Part 1",
    "studio": "21sextury",
    "series": "PixandVideo",
    "description": null,
    "img": "Tiffany Doll, Amirah Adara - After Hours Fun Part 1 [PixandVideo_21sextury] (2015_HD_466_76 MB).jpg",
    "url": "$mainstorage$\\Tiffany Doll, Amirah Adara - After Hours Fun Part 1 [PixandVideo_21sextury] (2015_HD_466_76 MB).mp4",
    "tags": [],
    "rank": 0,
    "addeddt": "2017-11-01T20:35:55.8953845+01:00",
    "size": 489435402,
    "Place": null,
    "Stars": [
      "Tiffany Doll",
      "Amirah Adara"
    ]
  },
  {
    "name": "The Helping Hand",
    "studio": "Relaxxxed",
    "series": null,
    "description": null,
    "img": "Vinna Reed, Amirah Adara - The Helping Hand [Relaxxxed] (16.06.18).jpg",
    "url": "$mainstorage$\\Vinna Reed, Amirah Adara - The Helping Hand [Relaxxxed] (16.06.18).mp4",
    "tags": [],
    "rank": 0,
    "addeddt": "2017-11-06T21:59:55.4505931+01:00",
    "size": 1863195760,
    "Place": null,
    "Stars": [
      "Vinna Reed",
      "Amirah Adara"
    ]
  }
]