[
  {
    "name": "Goblins In Her Gullet",
    "studio": "DDFNetwork",
    "series": "OnlyBlowJob",
    "description": null,
    "img": "Ava Dalush - Goblins In Her Gullet [OnlyBlowJob_DDFNetwork] (2014_SD_418_29 MB).jpg",
    "url": "$mainstorage$\\Ava Dalush - Goblins In Her Gullet [OnlyBlowJob_DDFNetwork] (2014_SD_418_29 MB).mp4",
    "tags": [],
    "rank": 0,
    "addeddt": "2017-11-01T20:35:24.6092769+01:00",
    "size": 438609279,
    "Place": null,
    "Stars": [
      "Ava Dalush"
    ]
  }
]