[
  {
    "name": "You look best undressed",
    "studio": "WTFPass",
    "series": "TheArtPorn",
    "description": null,
    "img": "Carolina Sweet - You look best undressed [TheArtPorn_WTFPass] (2017_FullHD_562_89 MB).jpg",
    "url": "$mainstorage$\\Carolina Sweet - You look best undressed [TheArtPorn_WTFPass] (2017_FullHD_562_89 MB).mp4",
    "tags": [
      "Anal"
    ],
    "rank": 0,
    "addeddt": "2017-11-01T20:35:27.5923341+01:00",
    "size": 590229634,
    "Place": null,
    "Stars": [
      "Carolina Sweet"
    ]
  }
]