[
  {
    "name": "Reality Sex With A Brunette Hottie",
    "studio": "MyPickupGirls",
    "series": null,
    "description": null,
    "img": "Elizabeth - Reality Sex With A Brunette Hottie [MyPickupGirls] (2011_HD_1_33 GB).jpg",
    "url": "$mainstorage$\\Elizabeth - Reality Sex With A Brunette Hottie [MyPickupGirls] (2011_HD_1_33 GB).mp4",
    "tags": [],
    "rank": 0,
    "addeddt": "2017-11-01T20:35:32.3081476+01:00",
    "size": 1427517135,
    "Place": null,
    "Stars": [
      "Elizabeth"
    ]
  },
  {
    "name": "Celebrating Exams With Hot College Sluts Part 5",
    "studio": "CollegeFuckParties",
    "series": null,
    "description": null,
    "img": "Tanata, Marya, Elizabeth, Kamila, Sveta - Celebrating Exams With Hot College Sluts Part 5 [CollegeFuckParties] (2011_HD_495_06 MB).jpg",
    "url": "$mainstorage$\\Tanata, Marya, Elizabeth, Kamila, Sveta - Celebrating Exams With Hot College Sluts Part 5 [CollegeFuckParties] (2011_HD_495_06 MB).mp4",
    "tags": [
      "Group"
    ],
    "rank": 0,
    "addeddt": "2017-11-01T20:35:55.4598599+01:00",
    "size": 1313636328,
    "Place": null,
    "Stars": [
      "Tanata",
      "Marya",
      "Elizabeth",
      "Kamila",
      "Sveta"
    ]
  }
]