[
  {
    "name": "The Writer - Sex Therapy",
    "studio": "SexArt",
    "series": null,
    "description": null,
    "img": "Alexis Brill, Luna, Whitney Conroy, Franck Franco - The Writer - Sex Therapy [SexArt] (2014_SD_526_34 MB).jpg",
    "url": "$mainstorage$\\Alexis Brill, Luna, Whitney Conroy, Franck Franco - The Writer - Sex Therapy [SexArt] (2014_SD_526_34 MB).mp4",
    "tags": [
      "Group"
    ],
    "rank": 0,
    "addeddt": "2017-11-01T20:35:20.5584408+01:00",
    "size": 551909540,
    "Place": null,
    "Stars": [
      "Alexis Brill",
      "Luna",
      "Whitney Conroy",
      "Franck Franco"
    ]
  }
]