[
  {
    "name": "Gentlemans Service_ Hot-Tempered Pampers Him From Head To Cock",
    "studio": "DDFNetwork",
    "series": "HotLegsAndFeet",
    "description": null,
    "img": "Julia Roca - Gentlemans Service_ Hot-Tempered Pampers Him From Head To Cock [HotLegsAndFeet_DDFNetwork] (2015_SD_653_63 MB).jpg",
    "url": "$mainstorage$\\Julia Roca - Gentlemans Service_ Hot-Tempered Pampers Him From Head To Cock [HotLegsAndFeet_DDFNetwork] (2015_SD_653_63 MB).mp4",
    "tags": [],
    "rank": 0,
    "addeddt": "2017-11-01T20:35:37.1902437+01:00",
    "size": 685378495,
    "Place": null,
    "Stars": [
      "Julia Roca"
    ]
  },
  {
    "name": "J and J",
    "studio": "SexArt",
    "series": null,
    "description": null,
    "img": "Julia Roca - J and J [SexArt] (2015_HD_729_63 MB).jpg",
    "url": "$mainstorage$\\Julia Roca - J and J [SexArt] (2015_HD_729_63 MB).mp4",
    "tags": [],
    "rank": 0,
    "addeddt": "2017-11-01T20:35:37.197243+01:00",
    "size": 765075172,
    "Place": null,
    "Stars": [
      "Julia Roca"
    ]
  },
  {
    "name": "Leaving The Car To Fuck",
    "studio": "PornPros",
    "series": "TeenBFF",
    "description": null,
    "img": "Julia Roca, Lola Reve - Leaving The Car To Fuck [TeenBFF_PornPros] (2014_SD_306_81 MB).jpg",
    "url": "$mainstorage$\\Julia Roca, Lola Reve - Leaving The Car To Fuck [TeenBFF_PornPros] (2014_SD_306_81 MB).mp4",
    "tags": [],
    "rank": 0,
    "addeddt": "2017-11-01T20:35:37.2042429+01:00",
    "size": 321716450,
    "Place": null,
    "Stars": [
      "Julia Roca",
      "Lola Reve"
    ]
  }
]