[
  {
    "name": "Two Roles For Lucy",
    "studio": "DDFNetwork",
    "series": "HouseOfTaboo",
    "description": null,
    "img": "Latex Lucy - Two Roles For Lucy [HouseOfTaboo_DDFNetwork] (2013_SD_515_19 MB).jpg",
    "url": "$mainstorage$\\Latex Lucy - Two Roles For Lucy [HouseOfTaboo_DDFNetwork] (2013_SD_515_19 MB).mp4",
    "tags": [],
    "rank": 0,
    "addeddt": "2017-11-01T20:35:40.2525224+01:00",
    "size": 860894496,
    "Place": null,
    "Stars": [
      "Latex Lucy"
    ]
  }
]