[
  {
    "name": "Beauty Saloon",
    "studio": "LittleCaprice",
    "series": null,
    "description": null,
    "img": "Little Caprice - Beauty Saloon [LittleCaprice] (2011_HD_808_64 MB).jpg",
    "url": "$mainstorage$\\Little Caprice - Beauty Saloon [LittleCaprice] (2011_HD_808_64 MB).wmv",
    "tags": [],
    "rank": 0,
    "addeddt": "2017-11-01T20:35:41.6726603+01:00",
    "size": 847925195,
    "Place": null,
    "Stars": [
      "Little Caprice"
    ]
  },
  {
    "name": "Intern’s Secret Perk!",
    "studio": "DDFNetwork",
    "series": null,
    "description": null,
    "img": "Little Caprice - Intern’s Secret Perk! [DDFNetwork] (2013).jpg",
    "url": "$mainstorage$\\Little Caprice - Intern’s Secret Perk! [DDFNetwork] (2013).mp4",
    "tags": [],
    "rank": 0,
    "addeddt": "2017-11-01T20:35:41.6816587+01:00",
    "size": 531653016,
    "Place": null,
    "Stars": [
      "Little Caprice"
    ]
  },
  {
    "name": "My First Time Going Black",
    "studio": "LittleCaprice-Dreams",
    "series": null,
    "description": null,
    "img": "Little Caprice - My First Time Going Black [LittleCaprice-Dreams] (2017_FullHD_1_54 GB).jpg",
    "url": "$mainstorage$\\Little Caprice - My First Time Going Black [LittleCaprice-Dreams] (2017_FullHD_1_54 GB).mp4",
    "tags": [
      "Black"
    ],
    "rank": 0,
    "addeddt": "2017-11-01T20:35:41.6896573+01:00",
    "size": 1648345866,
    "Place": null,
    "Stars": [
      "Little Caprice"
    ]
  },
  {
    "name": "ThreeSome",
    "studio": "LittleCaprice",
    "series": null,
    "description": null,
    "img": "Little Caprice - ThreeSome [LittleCaprice] (2011_HD_979_20 MB).jpg",
    "url": "$mainstorage$\\Little Caprice - ThreeSome [LittleCaprice] (2011_HD_979_20 MB).wmv",
    "tags": [],
    "rank": 0,
    "addeddt": "2017-11-01T20:35:41.6976586+01:00",
    "size": 1026766835,
    "Place": null,
    "Stars": [
      "Little Caprice"
    ]
  },
  {
    "name": "Hard Anal Games",
    "studio": "WoodmanCastingX",
    "series": null,
    "description": null,
    "img": "Rose Delight, Melisa A, Little Caprice - Hard Anal Games [WoodmanCastingX] (2012_SD_408_66 MB).jpg",
    "url": "$mainstorage$\\Rose Delight, Melisa A, Little Caprice - Hard Anal Games [WoodmanCastingX] (2012_SD_408_66 MB).mp4",
    "tags": [
      "Anal",
      "Group"
    ],
    "rank": 0,
    "addeddt": "2017-11-01T20:35:51.1921703+01:00",
    "size": 428508848,
    "Place": null,
    "Stars": [
      "Rose Delight",
      "Melisa A",
      "Little Caprice"
    ]
  }
]