[
  {
    "name": "Sandra Luberc",
    "studio": "21Sextury",
    "series": "AssHoleFever",
    "description": null,
    "img": "Sandra Luberc - Sandra Luberc [AssHoleFever_21Sextury] (2015_SD_471_48 MB).jpg",
    "url": "$mainstorage$\\Sandra Luberc - Sandra Luberc [AssHoleFever_21Sextury] (2015_SD_471_48 MB).mp4",
    "tags": [
      "Anal"
    ],
    "rank": 0,
    "addeddt": "2017-11-01T20:35:51.9986979+01:00",
    "size": 494378278,
    "Place": null,
    "Stars": [
      "Sandra Luberc"
    ]
  },
  {
    "name": "Tiny Girl On a Big Cock",
    "studio": "21Sextury",
    "series": "PixandVideo",
    "description": null,
    "img": "Sandra Luberc - Tiny Girl On a Big Cock [PixandVideo_21Sextury].jpg",
    "url": "$mainstorage$\\Sandra Luberc - Tiny Girl On a Big Cock [PixandVideo_21Sextury].mp4",
    "tags": [],
    "rank": 0,
    "addeddt": "2017-11-01T20:35:52.0076972+01:00",
    "size": 365063898,
    "Place": null,
    "Stars": [
      "Sandra Luberc"
    ]
  },
  {
    "name": "Persistence Pays",
    "studio": "DDFNetwork",
    "series": "EuroTeenErotica",
    "description": null,
    "img": "Sandra Luberc, Aurelly Rebel - Persistence Pays [EuroTeenErotica_DDFNetwork] (2013_SD_605_64 MB).jpg",
    "url": "$mainstorage$\\Sandra Luberc, Aurelly Rebel - Persistence Pays [EuroTeenErotica_DDFNetwork] (2013_SD_605_64 MB).mp4",
    "tags": [],
    "rank": 0,
    "addeddt": "2017-11-01T20:35:52.0356974+01:00",
    "size": 761115892,
    "Place": null,
    "Stars": [
      "Sandra Luberc",
      "Aurelly Rebel"
    ]
  },
  {
    "name": "Russian Anal Slut Sandra Luberc And Lola Bulgari In Hot Foursome With Double Penetration SZ1578",
    "studio": "LegalPorno",
    "series": null,
    "description": null,
    "img": "Sandra Luberc, Lola Bulgari - Russian Anal Slut Sandra Luberc And Lola Bulgari In Hot Foursome With Double Penetration SZ1578 [LegalPorno] (2017_HD_1_79 GB).jpg",
    "url": "$mainstorage$\\Sandra Luberc, Lola Bulgari - Russian Anal Slut Sandra Luberc And Lola Bulgari In Hot Foursome With Double Penetration SZ1578 [LegalPorno] (2017_HD_1_79 GB).mp4",
    "tags": [
      "Anal",
      "DP",
      "Group"
    ],
    "rank": 0,
    "addeddt": "2017-11-01T20:35:52.069696+01:00",
    "size": 540721484,
    "Place": null,
    "Stars": [
      "Sandra Luberc",
      "Lola Bulgari"
    ]
  },
  {
    "name": "Kreme surprise SZ272",
    "studio": "LegalPorno",
    "series": null,
    "description": null,
    "img": "Sandra Luberc, Timea Bella - Kreme surprise SZ272 [LegalPorno].jpg",
    "url": "$mainstorage$\\Sandra Luberc, Timea Bella - Kreme surprise SZ272 [LegalPorno].mp4",
    "tags": [],
    "rank": 0,
    "addeddt": "2017-11-01T20:35:52.0991974+01:00",
    "size": 1828963901,
    "Place": null,
    "Stars": [
      "Sandra Luberc",
      "Timea Bella"
    ]
  },
  {
    "name": "Timea, Tammy, Sandra Luberc Triple stacked , Fucked SZ382",
    "studio": "LegalPorno",
    "series": null,
    "description": null,
    "img": "Timea Bella, Sandra Luberc, Leona Levi - Timea, Tammy, Sandra Luberc Triple stacked , Fucked SZ382 [LegalPorno] (2015_HD_1_26 GB).jpg",
    "url": "$mainstorage$\\Timea Bella, Sandra Luberc, Leona Levi - Timea, Tammy, Sandra Luberc Triple stacked , Fucked SZ382 [LegalPorno] (2015_HD_1_26 GB).mp4",
    "tags": [
      "Group"
    ],
    "rank": 0,
    "addeddt": "2017-11-01T20:35:57.1643077+01:00",
    "size": 1357961346,
    "Place": null,
    "Stars": [
      "Timea Bella",
      "Sandra Luberc",
      "Leona Levi"
    ]
  }
]