[
  {
    "name": "Traum oder Real - Krasse Bestrafung",
    "studio": "MyDirtyHobby",
    "series": null,
    "description": null,
    "img": "SexyRia - Traum oder Real - Krasse Bestrafung [MyDirtyHobby] (2014_SD_404_31 MB).jpg",
    "url": "$mainstorage$\\SexyRia - Traum oder Real - Krasse Bestrafung [MyDirtyHobby] (2014_SD_404_31 MB).mp4",
    "tags": [
      "Anal"
    ],
    "rank": 0,
    "addeddt": "2017-11-01T20:35:52.6392916+01:00",
    "size": 423951132,
    "Place": null,
    "Stars": [
      "SexyRia"
    ]
  }
]