[
  {
    "name": "Shall I Bring My Girlfriend",
    "studio": "21Sextury",
    "series": "AssHoleFever",
    "description": null,
    "img": "Alice Romain, Vanda Lust - Shall I Bring My Girlfriend [AssHoleFever_21Sextury] (2013_SD_648_58 MB).jpg",
    "url": "$mainstorage$\\Alice Romain, Vanda Lust - Shall I Bring My Girlfriend [AssHoleFever_21Sextury] (2013_SD_648_58 MB).mp4",
    "tags": [
      "Anal"
    ],
    "rank": 0,
    "addeddt": "2017-11-01T20:35:20.9034615+01:00",
    "size": 663535834,
    "Place": null,
    "Stars": [
      "Alice Romain",
      "Vanda Lust"
    ]
  },
  {
    "name": "Walk on the Wild Side",
    "studio": "Babes",
    "series": null,
    "description": null,
    "img": "BabesKiara Lord, Vanda Lust, Ryan James - Walk on the Wild Side [Babes] (2014_SD_490_14 MB).jpg",
    "url": "$mainstorage$\\BabesKiara Lord, Vanda Lust, Ryan James - Walk on the Wild Side [Babes] (2014_SD_490_14 MB).mp4",
    "tags": [
      "Group"
    ],
    "rank": 0,
    "addeddt": "2017-11-01T20:35:24.8072776+01:00",
    "size": 513952418,
    "Place": null,
    "Stars": [
      "BabesKiara Lord",
      "Vanda Lust",
      "Ryan James"
    ]
  },
  {
    "name": "Making-Of - Young Horse Riders",
    "studio": "Dorcel",
    "series": null,
    "description": null,
    "img": "Cindy Hope, Cherry Kiss, Lana Fever, Sophie Lynx, Vanda Lust - Making-Of - Young Horse Riders [Dorcel].jpg",
    "url": "$mainstorage$\\Cindy Hope, Cherry Kiss, Lana Fever, Sophie Lynx, Vanda Lust - Making-Of - Young Horse Riders [Dorcel].mp4",
    "tags": [
      "Group"
    ],
    "rank": 0,
    "addeddt": "2017-11-01T20:35:29.6613778+01:00",
    "size": 330742992,
    "Place": null,
    "Stars": [
      "Cindy Hope",
      "Cherry Kiss",
      "Lana Fever",
      "Sophie Lynx",
      "Vanda Lust"
    ]
  },
  {
    "name": "Making of - Stewardesses",
    "studio": "DorcelClub",
    "series": null,
    "description": null,
    "img": "Claire Castel, Lola Reve, Vanda Lust, Alexis Crystal - Making of - Stewardesses [DorcelClub] (2015_FullHD_678_26 MB).jpg",
    "url": "$mainstorage$\\Claire Castel, Lola Reve, Vanda Lust, Alexis Crystal - Making of - Stewardesses [DorcelClub] (2015_FullHD_678_26 MB).mp4",
    "tags": [
      "Group"
    ],
    "rank": 0,
    "addeddt": "2017-11-01T20:35:30.1498776+01:00",
    "size": 711207314,
    "Place": null,
    "Stars": [
      "Claire Castel",
      "Lola Reve",
      "Vanda Lust",
      "Alexis Crystal"
    ]
  },
  {
    "name": "Danika and Vanda Lust",
    "studio": "DDFNetwork",
    "series": "HotLegsAndFeet",
    "description": null,
    "img": "Danika, Vanda Lust - Danika and Vanda Lust [HotLegsAndFeet_DDFNetwork] (2014_FullHD_1_69 GB).jpg",
    "url": "$mainstorage$\\Danika, Vanda Lust - Danika and Vanda Lust [HotLegsAndFeet_DDFNetwork] (2014_FullHD_1_69 GB).mp4",
    "tags": [],
    "rank": 0,
    "addeddt": "2017-11-01T20:35:30.8396353+01:00",
    "size": 1817033119,
    "Place": null,
    "Stars": [
      "Danika",
      "Vanda Lust"
    ]
  },
  {
    "name": "Feisty Freaks Dominate Their Bitchy Boss With Some Double Fisting And Sloppy Lesbo Fighting_",
    "studio": "SinDrive",
    "series": null,
    "description": null,
    "img": "Sophie Lynx, Tiffany Doll, Clare, Ivana Sugar, Vanda Lust - Feisty Freaks Dominate Their Bitchy Boss With Some Double Fisting And Sloppy Lesbo Fighting_ [SinDrive] (2014_SD_620_75 MB).jpg",
    "url": "$mainstorage$\\Sophie Lynx, Tiffany Doll, Clare, Ivana Sugar, Vanda Lust - Feisty Freaks Dominate Their Bitchy Boss With Some Double Fisting And Sloppy Lesbo Fighting_ [SinDrive] (2014_SD_620_75 MB).mp4",
    "tags": [
      "DP",
      "Group",
      "Anal",
      "Lesbian"
    ],
    "rank": 0,
    "addeddt": "2017-11-01T20:35:54.0454364+01:00",
    "size": 650901960,
    "Place": null,
    "Stars": [
      "Sophie Lynx",
      "Tiffany Doll",
      "Clare",
      "Ivana Sugar",
      "Vanda Lust"
    ]
  },
  {
    "name": "Dirty Divas Fight And Fuck In The Shower With Full Pervy Power",
    "studio": "SinDrive",
    "series": null,
    "description": null,
    "img": "Sophie Lynx, Vanda Lust - Dirty Divas Fight And Fuck In The Shower With Full Pervy Power [SinDrive] (2014_FullHD_1_46 GB).jpg",
    "url": "$mainstorage$\\Sophie Lynx, Vanda Lust - Dirty Divas Fight And Fuck In The Shower With Full Pervy Power [SinDrive] (2014_FullHD_1_46 GB).mp4",
    "tags": [],
    "rank": 0,
    "addeddt": "2017-11-01T20:35:54.0669392+01:00",
    "size": 491219866,
    "Place": null,
    "Stars": [
      "Sophie Lynx",
      "Vanda Lust"
    ]
  },
  {
    "name": "Asshole fever",
    "studio": "21Sextury",
    "series": "AssHoleFever",
    "description": null,
    "img": "Vanda Lust - Asshole fever [AssHoleFever_21Sextury] (2014_FullHD_667_76 MB).jpg",
    "url": "$mainstorage$\\Vanda Lust - Asshole fever [AssHoleFever_21Sextury] (2014_FullHD_667_76 MB).mp4",
    "tags": [
      "Anal"
    ],
    "rank": 0,
    "addeddt": "2017-11-01T20:35:59.4384245+01:00",
    "size": 700197310,
    "Place": null,
    "Stars": [
      "Vanda Lust"
    ]
  },
  {
    "name": "Backstage of If you have no money",
    "studio": "21sextury",
    "series": "PixandVideo",
    "description": null,
    "img": "Vanda Lust - Backstage of If you have no money [PixandVideo_21sextury] (2015_HD_620_23 MB).jpg",
    "url": "$mainstorage$\\Vanda Lust - Backstage of If you have no money [PixandVideo_21sextury] (2015_HD_620_23 MB).mp4",
    "tags": [],
    "rank": 0,
    "addeddt": "2017-11-01T20:35:59.4484247+01:00",
    "size": 650355772,
    "Place": null,
    "Stars": [
      "Vanda Lust"
    ]
  },
  {
    "name": "First Blowjob For a Young Virgin",
    "studio": "DorcelClub",
    "series": null,
    "description": null,
    "img": "Vanda Lust - First Blowjob For a Young Virgin [DorcelClub] (2014_HD_158_69 MB).jpg",
    "url": "$mainstorage$\\Vanda Lust - First Blowjob For a Young Virgin [DorcelClub] (2014_HD_158_69 MB).mp4",
    "tags": [],
    "rank": 0,
    "addeddt": "2017-11-01T20:35:59.4599249+01:00",
    "size": 216460465,
    "Place": null,
    "Stars": [
      "Vanda Lust"
    ]
  },
  {
    "name": "Garage Girl",
    "studio": "21sextury",
    "series": "AssHoleFever",
    "description": null,
    "img": "Vanda Lust - Garage Girl [AssHoleFever_21sextury] (2014_HD_394_06 MB).jpg",
    "url": "$mainstorage$\\Vanda Lust - Garage Girl [AssHoleFever_21sextury] (2014_HD_394_06 MB).mp4",
    "tags": [
      "Anal"
    ],
    "rank": 0,
    "addeddt": "2017-11-01T20:35:59.4744247+01:00",
    "size": 413204710,
    "Place": null,
    "Stars": [
      "Vanda Lust"
    ]
  },
  {
    "name": "Glamorous Like The Legend",
    "studio": "DDFNetwork",
    "series": null,
    "description": null,
    "img": "Vanda Lust - Glamorous Like The Legend [DDFNetwork] (2013).jpg",
    "url": "$mainstorage$\\Vanda Lust - Glamorous Like The Legend [DDFNetwork] (2013).mp4",
    "tags": [],
    "rank": 0,
    "addeddt": "2017-11-01T20:35:59.487925+01:00",
    "size": 1361459266,
    "Place": null,
    "Stars": [
      "Vanda Lust"
    ]
  },
  {
    "name": "Greedy Vanda",
    "studio": "21Sextury",
    "series": "DPFantastic",
    "description": null,
    "img": "Vanda Lust - Greedy Vanda [DPFantastic_21Sextury] (2013).jpg",
    "url": "$mainstorage$\\Vanda Lust - Greedy Vanda [DPFantastic_21Sextury] (2013).mp4",
    "tags": [
      "Group",
      "DP",
      "Anal"
    ],
    "rank": 0,
    "addeddt": "2017-11-01T20:35:59.5034254+01:00",
    "size": 507037817,
    "Place": null,
    "Stars": [
      "Vanda Lust"
    ]
  },
  {
    "name": "If You Have no Money",
    "studio": "21Sextury",
    "series": "PixAndVideo",
    "description": null,
    "img": "Vanda Lust - If You Have no Money [PixAndVideo_21Sextury] (2014_HD_656_52 MB).jpg",
    "url": "$mainstorage$\\Vanda Lust - If You Have no Money [PixAndVideo_21Sextury] (2014_HD_656_52 MB).mp4",
    "tags": [],
    "rank": 0,
    "addeddt": "2017-11-01T20:35:59.528425+01:00",
    "size": 688413542,
    "Place": null,
    "Stars": [
      "Vanda Lust"
    ]
  },
  {
    "name": "Kitchen Romance",
    "studio": "21FootArt",
    "series": null,
    "description": null,
    "img": "Vanda Lust - Kitchen Romance [21FootArt] (2015_SD_686_33 MB).jpg",
    "url": "$mainstorage$\\Vanda Lust - Kitchen Romance [21FootArt] (2015_SD_686_33 MB).mp4",
    "tags": [],
    "rank": 0,
    "addeddt": "2017-11-01T20:35:59.5414254+01:00",
    "size": 1516839096,
    "Place": null,
    "Stars": [
      "Vanda Lust"
    ]
  },
  {
    "name": "Line Up Boys!",
    "studio": "WowPorn",
    "series": null,
    "description": null,
    "img": "Vanda Lust - Line Up Boys! [WowPorn].jpg",
    "url": "$mainstorage$\\Vanda Lust - Line Up Boys! [WowPorn].mp4",
    "tags": [],
    "rank": 0,
    "addeddt": "2017-11-01T20:35:59.5524246+01:00",
    "size": 914364431,
    "Place": null,
    "Stars": [
      "Vanda Lust"
    ]
  },
  {
    "name": "Luck Of The Plumber! -",
    "studio": "DDFNetwork",
    "series": "HandsOnHardcore",
    "description": null,
    "img": "Vanda Lust - Luck Of The Plumber! - [HandsOnHardcore_DDFNetwork] (2013 HD).jpg",
    "url": "$mainstorage$\\Vanda Lust - Luck Of The Plumber! - [HandsOnHardcore_DDFNetwork] (2013 HD).mp4",
    "tags": [],
    "rank": 0,
    "addeddt": "2017-11-01T20:35:59.5639245+01:00",
    "size": 1220476962,
    "Place": null,
    "Stars": [
      "Vanda Lust"
    ]
  },
  {
    "name": "Porn Casting",
    "studio": "My-Porn-Casting-And-Audition",
    "series": null,
    "description": null,
    "img": "Vanda Lust - Porn Casting [My-Porn-Casting-And-Audition] (2015_SD_408_52 MB).jpg",
    "url": "$mainstorage$\\Vanda Lust - Porn Casting [My-Porn-Casting-And-Audition] (2015_SD_408_52 MB).mp4",
    "tags": [],
    "rank": 0,
    "addeddt": "2017-11-01T20:35:59.5729248+01:00",
    "size": 428360080,
    "Place": null,
    "Stars": [
      "Vanda Lust"
    ]
  },
  {
    "name": "Rookie girl",
    "studio": "21Sextury",
    "series": "PixAndVideo",
    "description": null,
    "img": "Vanda Lust - Rookie girl [PixAndVideo_21Sextury].jpg",
    "url": "$mainstorage$\\Vanda Lust - Rookie girl [PixAndVideo_21Sextury].wmv",
    "tags": [],
    "rank": 0,
    "addeddt": "2017-11-01T20:35:59.5829241+01:00",
    "size": 682516600,
    "Place": null,
    "Stars": [
      "Vanda Lust"
    ]
  },
  {
    "name": "Seasoned Cock, Young Twat Vanda Lust v40288-499",
    "studio": "21Sextury",
    "series": "GrandpasFuckTeens",
    "description": null,
    "img": "Vanda Lust - Seasoned Cock, Young Twat Vanda Lust v40288-499 [GrandpasFuckTeens_21Sextury].jpg",
    "url": "$mainstorage$\\Vanda Lust - Seasoned Cock, Young Twat Vanda Lust v40288-499 [GrandpasFuckTeens_21Sextury].mp4",
    "tags": [
      "Group",
      "DP",
      "Anal"
    ],
    "rank": 0,
    "addeddt": "2017-11-01T20:35:59.5909235+01:00",
    "size": 885009439,
    "Place": null,
    "Stars": [
      "Vanda Lust"
    ]
  },
  {
    "name": "Solo in uniform",
    "studio": "DDFNetwork",
    "series": null,
    "description": null,
    "img": "Vanda Lust - Solo in uniform [DDFNetwork].jpg",
    "url": "$mainstorage$\\Vanda Lust - Solo in uniform [DDFNetwork].mp4",
    "tags": [],
    "rank": 0,
    "addeddt": "2017-11-01T20:35:59.6019264+01:00",
    "size": 465766201,
    "Place": null,
    "Stars": [
      "Vanda Lust"
    ]
  },
  {
    "name": "Surprise",
    "studio": "SexArt",
    "series": null,
    "description": null,
    "img": "Vanda Lust - Surprise [SexArt] (2014_SD_280_59 MB).jpg",
    "url": "$mainstorage$\\Vanda Lust - Surprise [SexArt] (2014_SD_280_59 MB).mp4",
    "tags": [],
    "rank": 0,
    "addeddt": "2017-11-01T20:35:59.6129243+01:00",
    "size": 294215493,
    "Place": null,
    "Stars": [
      "Vanda Lust"
    ]
  },
  {
    "name": "Take Your Pecker To College",
    "studio": "DDFNetwork",
    "series": "OnlyBlowJob",
    "description": null,
    "img": "Vanda Lust - Take Your Pecker To College [OnlyBlowJob_DDFNetwork].jpg",
    "url": "$mainstorage$\\Vanda Lust - Take Your Pecker To College [OnlyBlowJob_DDFNetwork].mp4",
    "tags": [],
    "rank": 0,
    "addeddt": "2017-11-01T20:35:59.6279243+01:00",
    "size": 474097951,
    "Place": null,
    "Stars": [
      "Vanda Lust"
    ]
  },
  {
    "name": "The Christmas Tree Disaster",
    "studio": "Oldje",
    "series": null,
    "description": null,
    "img": "Vanda Lust - The Christmas Tree Disaster [Oldje].jpg",
    "url": "$mainstorage$\\Vanda Lust - The Christmas Tree Disaster [Oldje].wmv",
    "tags": [],
    "rank": 0,
    "addeddt": "2017-11-01T20:35:59.6374265+01:00",
    "size": 412112169,
    "Place": null,
    "Stars": [
      "Vanda Lust"
    ]
  },
  {
    "name": "The Cleaning model version 1.0",
    "studio": "Oldje",
    "series": null,
    "description": null,
    "img": "Vanda Lust - The Cleaning model version 1.0 [Oldje].jpg",
    "url": "$mainstorage$\\Vanda Lust - The Cleaning model version 1.0 [Oldje].wmv",
    "tags": [],
    "rank": 0,
    "addeddt": "2017-11-01T20:35:59.6479244+01:00",
    "size": 651710205,
    "Place": null,
    "Stars": [
      "Vanda Lust"
    ]
  },
  {
    "name": "Toys and lust big",
    "studio": "RealityKings",
    "series": null,
    "description": null,
    "img": "Vanda Lust - Toys and lust big [RealityKings].jpg",
    "url": "$mainstorage$\\Vanda Lust - Toys and lust big [RealityKings].mp4",
    "tags": [],
    "rank": 0,
    "addeddt": "2017-11-01T20:35:59.6594233+01:00",
    "size": 510251699,
    "Place": null,
    "Stars": [
      "Vanda Lust"
    ]
  },
  {
    "name": "Vanda goes crazy",
    "studio": "21sextreme",
    "series": "Zoliboy",
    "description": null,
    "img": "Vanda Lust - Vanda goes crazy [Zoliboy_21sextreme] (2013_SD_341_82 MB).jpg",
    "url": "$mainstorage$\\Vanda Lust - Vanda goes crazy [Zoliboy_21sextreme] (2013_SD_341_82 MB).mp4",
    "tags": [],
    "rank": 0,
    "addeddt": "2017-11-01T20:35:59.6699246+01:00",
    "size": 358427082,
    "Place": null,
    "Stars": [
      "Vanda Lust"
    ]
  },
  {
    "name": "Vanda Lust European Nude",
    "studio": "Culioneros",
    "series": null,
    "description": null,
    "img": "Vanda Lust - Vanda Lust European Nude [Culioneros].jpg",
    "url": "$mainstorage$\\Vanda Lust - Vanda Lust European Nude [Culioneros].mp4",
    "tags": [],
    "rank": 0,
    "addeddt": "2017-11-01T20:35:59.6809249+01:00",
    "size": 333897883,
    "Place": null,
    "Stars": [
      "Vanda Lust"
    ]
  },
  {
    "name": "Vanda Lust in AssHoleFever",
    "studio": "21Sextury",
    "series": "AssHoleFever",
    "description": null,
    "img": "Vanda Lust - Vanda Lust in AssHoleFever [AssHoleFever_21Sextury] (2013).jpg",
    "url": "$mainstorage$\\Vanda Lust - Vanda Lust in AssHoleFever [AssHoleFever_21Sextury] (2013).mp4",
    "tags": [
      "Anal"
    ],
    "rank": 0,
    "addeddt": "2017-11-01T20:35:59.6979241+01:00",
    "size": 1027002493,
    "Place": null,
    "Stars": [
      "Vanda Lust"
    ]
  },
  {
    "name": "Vanda Lust in Love, Sex Unity",
    "studio": "21Sextury",
    "series": "AssHoleFever",
    "description": null,
    "img": "Vanda Lust - Vanda Lust in Love, Sex Unity [AssHoleFever_21Sextury] (2014_SD_404_88 MB).jpg",
    "url": "$mainstorage$\\Vanda Lust - Vanda Lust in Love, Sex Unity [AssHoleFever_21Sextury] (2014_SD_404_88 MB).mp4",
    "tags": [
      "Anal"
    ],
    "rank": 0,
    "addeddt": "2017-11-01T20:35:59.7129244+01:00",
    "size": 424552095,
    "Place": null,
    "Stars": [
      "Vanda Lust"
    ]
  },
  {
    "name": "Vander passes her audition part 1",
    "studio": "JimSlip",
    "series": null,
    "description": null,
    "img": "Vanda Lust - Vander passes her audition part 1 [JimSlip].jpg",
    "url": "$mainstorage$\\Vanda Lust - Vander passes her audition part 1 [JimSlip].wmv",
    "tags": [
      "Anal"
    ],
    "rank": 0,
    "addeddt": "2017-11-01T20:35:59.7289996+01:00",
    "size": 855484096,
    "Place": null,
    "Stars": [
      "Vanda Lust"
    ]
  },
  {
    "name": "Vander passes her audition part 2",
    "studio": "JimSlip",
    "series": null,
    "description": null,
    "img": "Vanda Lust - Vander passes her audition part 2 [JimSlip].jpg",
    "url": "$mainstorage$\\Vanda Lust - Vander passes her audition part 2 [JimSlip].wmv",
    "tags": [
      "Anal"
    ],
    "rank": 0,
    "addeddt": "2017-11-01T20:35:59.7421021+01:00",
    "size": 879173480,
    "Place": null,
    "Stars": [
      "Vanda Lust"
    ]
  },
  {
    "name": "Champagne and anal sex at Ibiza",
    "studio": "DorcelClub",
    "series": null,
    "description": null,
    "img": "Vanda Lust, Alexis Crystal - Champagne and anal sex at Ibiza [DorcelClub] (2015_HD_355_21 MB).jpg",
    "url": "$mainstorage$\\Vanda Lust, Alexis Crystal - Champagne and anal sex at Ibiza [DorcelClub] (2015_HD_355_21 MB).mp4",
    "tags": [
      "Anal"
    ],
    "rank": 0,
    "addeddt": "2017-11-01T20:35:59.7550971+01:00",
    "size": 372468841,
    "Place": null,
    "Stars": [
      "Vanda Lust",
      "Alexis Crystal"
    ]
  },
  {
    "name": "Naughty Sex Fantasies, Scene 1",
    "studio": "Doghousedigital",
    "series": null,
    "description": null,
    "img": "Vanda Lust, Alice Romain - Naughty Sex Fantasies, Scene 1 [Doghousedigital].jpg",
    "url": "$mainstorage$\\Vanda Lust, Alice Romain - Naughty Sex Fantasies, Scene 1 [Doghousedigital].mp4",
    "tags": [],
    "rank": 0,
    "addeddt": "2017-11-01T20:35:59.8016+01:00",
    "size": 488426787,
    "Place": null,
    "Stars": [
      "Vanda Lust",
      "Alice Romain"
    ]
  },
  {
    "name": "Shall I Bring a Girlfriend",
    "studio": "21Sextury",
    "series": "AssholeFever",
    "description": null,
    "img": "Vanda Lust, Alice Romain - Shall I Bring a Girlfriend [AssholeFever_21Sextury].jpg",
    "url": "$mainstorage$\\Vanda Lust, Alice Romain - Shall I Bring a Girlfriend [AssholeFever_21Sextury].wmv",
    "tags": [
      "Anal"
    ],
    "rank": 0,
    "addeddt": "2017-11-01T20:35:59.8290986+01:00",
    "size": 1062903111,
    "Place": null,
    "Stars": [
      "Vanda Lust",
      "Alice Romain"
    ]
  },
  {
    "name": "Andie Darling And Vanda Ass To Ass Video SZ241",
    "studio": "Sineplex",
    "series": "LegalPorno",
    "description": null,
    "img": "Vanda Lust, Andie Darling - Andie Darling And Vanda Ass To Ass Video SZ241 [LegalPorno_Sineplex] (2014_HD_1_40 GB).jpg",
    "url": "$mainstorage$\\Vanda Lust, Andie Darling - Andie Darling And Vanda Ass To Ass Video SZ241 [LegalPorno_Sineplex] (2014_HD_1_40 GB).mp4",
    "tags": [
      "Anal"
    ],
    "rank": 0,
    "addeddt": "2017-11-01T20:35:59.8620985+01:00",
    "size": 1508173687,
    "Place": null,
    "Stars": [
      "Vanda Lust",
      "Andie Darling"
    ]
  },
  {
    "name": "Triple cream enema SZ418",
    "studio": "LegalPorno",
    "series": null,
    "description": null,
    "img": "Vanda Lust, Angel Blonde, Lucy Heart - Triple cream enema SZ418 [LegalPorno].jpg",
    "url": "$mainstorage$\\Vanda Lust, Angel Blonde, Lucy Heart - Triple cream enema SZ418 [LegalPorno].mp4",
    "tags": [
      "Group"
    ],
    "rank": 0,
    "addeddt": "2017-11-01T20:35:59.8835986+01:00",
    "size": 2251520170,
    "Place": null,
    "Stars": [
      "Vanda Lust",
      "Angel Blonde",
      "Lucy Heart"
    ]
  },
  {
    "name": "Vanda Lust and Blanche Bradburry",
    "studio": "DDFProd",
    "series": "EuroGirlsOnGirls",
    "description": null,
    "img": "Vanda Lust, Blanche Bradburry - Vanda Lust and Blanche Bradburry [EuroGirlsOnGirls_DDFProd] (2014_SD_470_24 MB).jpg",
    "url": "$mainstorage$\\Vanda Lust, Blanche Bradburry - Vanda Lust and Blanche Bradburry [EuroGirlsOnGirls_DDFProd] (2014_SD_470_24 MB).mp4",
    "tags": [],
    "rank": 0,
    "addeddt": "2017-11-01T20:35:59.9255979+01:00",
    "size": 493087475,
    "Place": null,
    "Stars": [
      "Vanda Lust",
      "Blanche Bradburry"
    ]
  },
  {
    "name": "Hot beauties Cayenne Klein and Vanda Lust sharing a huge dick",
    "studio": "DDFNetwork",
    "series": null,
    "description": null,
    "img": "Vanda Lust, Cayenne Klein - Hot beauties Cayenne Klein and Vanda Lust sharing a huge dick [DDFNetwork].jpg",
    "url": "$mainstorage$\\Vanda Lust, Cayenne Klein - Hot beauties Cayenne Klein and Vanda Lust sharing a huge dick [DDFNetwork].mp4",
    "tags": [],
    "rank": 0,
    "addeddt": "2017-11-01T20:35:59.9750976+01:00",
    "size": 431606969,
    "Place": null,
    "Stars": [
      "Vanda Lust",
      "Cayenne Klein"
    ]
  },
  {
    "name": "The Life of a Golden Boy - part 1_",
    "studio": "21Sextury",
    "series": "PixandVideo",
    "description": null,
    "img": "Vanda Lust, Hannah Sweet - The Life of a Golden Boy - part 1_ [PixandVideo_21Sextury] (2014_SD_354_29 MB).jpg",
    "url": "$mainstorage$\\Vanda Lust, Hannah Sweet - The Life of a Golden Boy - part 1_ [PixandVideo_21Sextury] (2014_SD_354_29 MB).mp4",
    "tags": [],
    "rank": 0,
    "addeddt": "2017-11-01T20:36:00.0285986+01:00",
    "size": 371495955,
    "Place": null,
    "Stars": [
      "Vanda Lust",
      "Hannah Sweet"
    ]
  },
  {
    "name": "The Life of a Golden Boy - part 2",
    "studio": "21sextury",
    "series": "PixandVideo",
    "description": null,
    "img": "Vanda Lust, Hannah Sweet - The Life of a Golden Boy - part 2 [PixandVideo_21sextury] (2014_HD_533_84 MB).jpg",
    "url": "$mainstorage$\\Vanda Lust, Hannah Sweet - The Life of a Golden Boy - part 2 [PixandVideo_21sextury] (2014_HD_533_84 MB).mp4",
    "tags": [],
    "rank": 0,
    "addeddt": "2017-11-01T20:36:00.0515981+01:00",
    "size": 559767664,
    "Place": null,
    "Stars": [
      "Vanda Lust",
      "Hannah Sweet"
    ]
  },
  {
    "name": "Fucked by 3 cocks SZ393",
    "studio": "LegalPorno",
    "series": null,
    "description": null,
    "img": "Vanda Lust, Ivana Sugar, Melissa - Fucked by 3 cocks SZ393 [LegalPorno] (2013_SD_756_06 MB).jpg",
    "url": "$mainstorage$\\Vanda Lust, Ivana Sugar, Melissa - Fucked by 3 cocks SZ393 [LegalPorno] (2013_SD_756_06 MB).mp4",
    "tags": [
      "Group"
    ],
    "rank": 0,
    "addeddt": "2017-11-01T20:36:00.0716003+01:00",
    "size": 792790477,
    "Place": null,
    "Stars": [
      "Vanda Lust",
      "Ivana Sugar",
      "Melissa"
    ]
  },
  {
    "name": "When The Teacher's Away",
    "studio": "DDFNetwork",
    "series": "EuroGirlsOnGirls",
    "description": null,
    "img": "Vanda Lust, Marica Hase - When The Teacher's Away [EuroGirlsOnGirls_DDFNetwork] (2013).jpg",
    "url": "$mainstorage$\\Vanda Lust, Marica Hase - When The Teacher's Away [EuroGirlsOnGirls_DDFNetwork] (2013).mp4",
    "tags": [],
    "rank": 0,
    "addeddt": "2017-11-01T20:36:00.1130998+01:00",
    "size": 1040504738,
    "Place": null,
    "Stars": [
      "Vanda Lust",
      "Marica Hase"
    ]
  },
  {
    "name": "RoccoSiffredi Butt Fucks his 2 Slaves",
    "studio": "EvilAngel",
    "series": "RoccoSiffredi",
    "description": null,
    "img": "Vanda Lust, Nataly Gold - RoccoSiffredi Butt Fucks his 2 Slaves [RoccoSiffredi_EvilAngel].jpg",
    "url": "$mainstorage$\\Vanda Lust, Nataly Gold - RoccoSiffredi Butt Fucks his 2 Slaves [RoccoSiffredi_EvilAngel].mp4",
    "tags": [
      "Anal"
    ],
    "rank": 0,
    "addeddt": "2017-11-01T20:36:00.1385982+01:00",
    "size": 1348815056,
    "Place": null,
    "Stars": [
      "Vanda Lust",
      "Nataly Gold"
    ]
  },
  {
    "name": "Fuck Fantasy with Vanda Lust",
    "studio": "21Sextreme",
    "series": "Zoliboy",
    "description": null,
    "img": "Vanda Lust, Nesty - Fuck Fantasy with Vanda Lust [Zoliboy_21Sextreme] (2014_FullHD_1_00 GB).jpg",
    "url": "$mainstorage$\\Vanda Lust, Nesty - Fuck Fantasy with Vanda Lust [Zoliboy_21Sextreme] (2014_FullHD_1_00 GB).mp4",
    "tags": [],
    "rank": 0,
    "addeddt": "2017-11-01T20:36:00.1765986+01:00",
    "size": 1075752836,
    "Place": null,
    "Stars": [
      "Vanda Lust",
      "Nesty"
    ]
  },
  {
    "name": "Licking and sticking",
    "studio": "RealityKings",
    "series": "EuroSexParties",
    "description": null,
    "img": "Vanda Lust, Sophie Lynx - Licking and sticking [EuroSexParties_RealityKings] (2014_SD_1_01 GB).jpg",
    "url": "$mainstorage$\\Vanda Lust, Sophie Lynx - Licking and sticking [EuroSexParties_RealityKings] (2014_SD_1_01 GB).mp4",
    "tags": [],
    "rank": 0,
    "addeddt": "2017-11-01T20:36:00.2065989+01:00",
    "size": 1089529901,
    "Place": null,
    "Stars": [
      "Vanda Lust",
      "Sophie Lynx"
    ]
  },
  {
    "name": "The Window Wolf",
    "studio": "DDFNetwork",
    "series": "HandsOnHardcore",
    "description": null,
    "img": "Vanda Lust, Stella Cox - The Window Wolf [HandsOnHardcore_DDFNetwork] (2015_SD_1_11 GB).jpg",
    "url": "$mainstorage$\\Vanda Lust, Stella Cox - The Window Wolf [HandsOnHardcore_DDFNetwork] (2015_SD_1_11 GB).mp4",
    "tags": [],
    "rank": 0,
    "addeddt": "2017-11-01T20:36:00.2485997+01:00",
    "size": 1190977189,
    "Place": null,
    "Stars": [
      "Vanda Lust",
      "Stella Cox"
    ]
  },
  {
    "name": "Vanda Lust and Stella Cox",
    "studio": "DDFNetwork",
    "series": "HandsOnHardcore",
    "description": null,
    "img": "Vanda Lust, Stella Cox - Vanda Lust and Stella Cox [HandsOnHardcore_DDFNetwork] (720p).jpg",
    "url": "$mainstorage$\\Vanda Lust, Stella Cox - Vanda Lust and Stella Cox [HandsOnHardcore_DDFNetwork] (720p).mp4",
    "tags": [],
    "rank": 0,
    "addeddt": "2017-11-01T20:36:00.2710041+01:00",
    "size": 601669720,
    "Place": null,
    "Stars": [
      "Vanda Lust",
      "Stella Cox"
    ]
  },
  {
    "name": "Blue Bedroom Eyes",
    "studio": "DDFNetwork",
    "series": "HandsOnHardcore",
    "description": null,
    "img": "Vanda Lust, Totti, Mugur - Blue Bedroom Eyes [HandsOnHardcore_DDFNetwork].jpg",
    "url": "$mainstorage$\\Vanda Lust, Totti, Mugur - Blue Bedroom Eyes [HandsOnHardcore_DDFNetwork].mp4",
    "tags": [
      "Group"
    ],
    "rank": 0,
    "addeddt": "2017-11-01T20:36:00.2960049+01:00",
    "size": 1396925685,
    "Place": null,
    "Stars": [
      "Vanda Lust",
      "Totti",
      "Mugur"
    ]
  },
  {
    "name": "Hot Girls in Stockings",
    "studio": "21Sextury",
    "series": "TheVeryBestOf",
    "description": null,
    "img": "Destiny, Vanda Lust, Angelica Heart, Martina Gold, Sensual Jane, Sophie Lynx - Hot Girls in Stockings [TheVeryBestOf_21Sextury] (2017_HD_1_36 GB).jpg",
    "url": "$mainstorage$\\Destiny, Vanda Lust, Angelica Heart, Martina Gold, Sensual Jane, Sophie Lynx - Hot Girls in Stockings [TheVeryBestOf_21Sextury] (2017_HD_1_36 GB).mp4",
    "tags": [
      "Stocking",
      "Group"
    ],
    "rank": 0,
    "addeddt": "2017-11-22T18:06:10.3302504+01:00",
    "size": 1459051673,
    "Place": null,
    "Stars": [
      "Destiny",
      "Vanda Lust",
      "Angelica Heart",
      "Martina Gold",
      "Sensual Jane",
      "Sophie Lynx"
    ]
  }
]