[
  {
    "name": "Collegues DP Schoolgirl, Costumed Veronica",
    "studio": "21Sextury",
    "series": "DPFanatics",
    "description": null,
    "img": "Veronica Morre - Collegues DP Schoolgirl, Costumed Veronica [DPFanatics_21Sextury] (Feb_21_2016).jpg",
    "url": "$mainstorage$\\Veronica Morre - Collegues DP Schoolgirl, Costumed Veronica [DPFanatics_21Sextury] (Feb_21_2016).mp4",
    "tags": [
      "DP",
      "Group",
      "Anal"
    ],
    "rank": 0,
    "addeddt": "2017-11-01T20:36:00.6290038+01:00",
    "size": 744838365,
    "Place": null,
    "Stars": [
      "Veronica Morre"
    ]
  }
]