[
  {
    "name": "Barbamiska and Verunka",
    "studio": "21Sextury",
    "series": "AnalTeenAngels",
    "description": null,
    "img": "Barbamiska, Verunka - Barbamiska and Verunka [AnalTeenAngels_21Sextury] (2009_SD_576_68 MB).jpg",
    "url": "$mainstorage$\\Barbamiska, Verunka - Barbamiska and Verunka [AnalTeenAngels_21Sextury] (2009_SD_576_68 MB).mp4",
    "tags": [
      "Anal"
    ],
    "rank": 0,
    "addeddt": "2017-11-01T20:35:24.8612763+01:00",
    "size": 604689332,
    "Place": null,
    "Stars": [
      "Barbamiska",
      "Verunka"
    ]
  },
  {
    "name": "Busty Russians",
    "studio": "21Sextury",
    "series": "TheVeryBestOf",
    "description": null,
    "img": "Sunny, Sneila, Iyana, Luna, Dalila, Lydia, Mandi Dee, Verunka - Busty Russians [TheVeryBestOf_21Sextury] (2014_SD_320_27 MB).jpg",
    "url": "$mainstorage$\\Sunny, Sneila, Iyana, Luna, Dalila, Lydia, Mandi Dee, Verunka - Busty Russians [TheVeryBestOf_21Sextury] (2014_SD_320_27 MB).mp4",
    "tags": [
      "Group"
    ],
    "rank": 0,
    "addeddt": "2017-11-01T20:35:50.6671692+01:00",
    "size": 571254851,
    "Place": null,
    "Stars": [
      "Sunny",
      "Sneila",
      "Iyana",
      "Luna",
      "Dalila",
      "Lydia",
      "Mandi Dee",
      "Verunka"
    ]
  }
]